ecs_service_discovery/__init__.py
ecs_service_discovery/cli.py
ecs_service_discovery/ecs_sd_common.py
ecs_service_discovery/ecs_service_discovery.py
ecs_service_discovery/prometheus_sd.py
ecs_service_discovery/stats.py
ecs_service_discovery-0.1.4.dist-info/LICENSE
ecs_service_discovery-0.1.4.dist-info/METADATA
ecs_service_discovery-0.1.4.dist-info/WHEEL
ecs_service_discovery-0.1.4.dist-info/entry_points.txt
ecs_service_discovery-0.1.4.dist-info/RECORD
