Metadata-Version: 2.1
Name: ecs_service_discovery
Version: 0.1.4
Summary: ECS Service Discovery
License: MPL-2.0
Keywords: ecs,service discovery,observability
Author: John Preston
Author-email: john@ews-network.net
Requires-Python: >=3.9,<4.0
Classifier: Development Status :: 4 - Beta
Classifier: Intended Audience :: Developers
Classifier: Intended Audience :: Information Technology
Classifier: Intended Audience :: System Administrators
Classifier: License :: OSI Approved
Classifier: License :: OSI Approved :: Mozilla Public License 2.0 (MPL 2.0)
Classifier: Natural Language :: English
Classifier: Programming Language :: Python :: 3
Classifier: Programming Language :: Python :: 3.9
Classifier: Programming Language :: Python :: 3.10
Classifier: Programming Language :: Python :: 3.11
Classifier: Programming Language :: Python :: 3.12
Classifier: Programming Language :: Python :: 3.8
Requires-Dist: PyYAML (>=6.0,<7.0)
Requires-Dist: compose-x-common (>=1.2,<2.0)
Requires-Dist: prometheus-client (>=0.20,<0.21)
Project-URL: Bug Tracker, https://github.com/compose-x/ecs-service-discovery/issues
Project-URL: Blog, https://blog.compose-x.io/
Project-URL: Labs, https://labs.compose-x.io/
Project-URL: Source, https://github.com/compose-x/ecs-service-discovery/
